interval_tree/__init__.py
interval_tree/interval_tree.py
interval_tree-0.3.4.dist-info/DESCRIPTION.rst
interval_tree-0.3.4.dist-info/METADATA
interval_tree-0.3.4.dist-info/RECORD
interval_tree-0.3.4.dist-info/WHEEL
interval_tree-0.3.4.dist-info/metadata.json
interval_tree-0.3.4.dist-info/top_level.txt
